Changes.rst
LICENSE
README.rst
pyproject.toml
setup.cfg
setup.py
Include/fuse_common.pxd
Include/fuse_lowlevel.pxd
Include/fuse_opt.pxd
Include/pthread.pxd
Include/libc/__init__.py
Include/libc/dirent.pxd
Include/libc/sys/__init__.py
Include/libc/sys/statvfs.pxd
examples/lltest.py
examples/passthroughfs.py
examples/tmpfs.py
rst/about.rst
rst/changes.rst
rst/conf.py
rst/data.rst
rst/example.rst
rst/fuse_api.rst
rst/general.rst
rst/gotchas.rst
rst/index.rst
rst/install.rst
rst/lock.rst
rst/operations.rst
rst/util.rst
rst/_static/.placeholder
rst/_templates/localtoc.html
src/darwin_compat.c
src/darwin_compat.h
src/fuse_api.pxi
src/gettime.h
src/handlers.pxi
src/llfuse.c
src/llfuse.h
src/llfuse.pyx
src/lock.c
src/lock.h
src/macros.c
src/misc.pxi
src/operations.pxi
src/xattr.h
src/arvados_llfuse.egg-info/PKG-INFO
src/arvados_llfuse.egg-info/SOURCES.txt
src/arvados_llfuse.egg-info/dependency_links.txt
src/arvados_llfuse.egg-info/top_level.txt
src/arvados_llfuse.egg-info/zip-safe
test/conftest.py
test/pytest.ini
test/pytest_checklogs.py
test/test_api.py
test/test_examples.py
test/test_fs.py
test/test_rounding.py
test/util.py
util/sdist-sign
util/sphinx_cython.py
util/upload-pypi